afaas/__init__.py
afaas/cache/__init__.py
afaas/cache/cache.py
afaas/cache/tests/__init__.py
afaas/cache/tests/data/empty.fasta
afaas/cache/tests/test_cache.py
afaas/common/__init__.py
afaas/common/http_server.py
afaas/common/tests/__init__.py
afaas/common/tests/data/test_creds.json
afaas/common/tests/data/test_server_creds.json
afaas/common/tests/utils.py
afaas/common/utils.py
afaas/tests/__init__.py
afaas/tests/helpers.py
afaas/tests/pytest.ini
afaas_common-0.3.8.dist-info/WHEEL
afaas_common-0.3.8.dist-info/METADATA
afaas_common-0.3.8.dist-info/RECORD
