Metadata-Version: 2.1
Name: afaas-common
Version: 0.3.8
Summary: Alphafold as a Service common packages
Author: Cradle Bio
Author-email: info@cradle.bio
Requires-Python: >=3.8,<3.11
Classifier: Programming Language :: Python :: 3
Classifier: Programming Language :: Python :: 3.8
Classifier: Programming Language :: Python :: 3.9
Classifier: Programming Language :: Python :: 3.10
Requires-Dist: biopython (>=1.79,<2.0)
Requires-Dist: google-cloud-firestore (>=2.4.0,<3.0.0)
Requires-Dist: protobuf (==3.20.3)
